setup.cfg
setup.py
repool/__init__.py
repool/pool.py
repool.egg-info/PKG-INFO
repool.egg-info/SOURCES.txt
repool.egg-info/dependency_links.txt
repool.egg-info/requires.txt
repool.egg-info/top_level.txt