Metadata-Version: 1.1
Name: repool
Version: 0.0.4
Summary: Connection pool for rethinkdb
Home-page: https://github.com/njouanin/repool
Author: Nicolas Jouanin
Author-email: nicolas.jouanin@gmail.com
License: GPLv3
Platform: UNKNOWN
Classifier: Development Status :: 2 - Pre-Alpha
Classifier: Intended Audience :: Developers
Classifier: License :: OSI Approved :: GNU General Public License v3 (GPLv3)
Classifier: Operating System :: POSIX :: Linux
Classifier: Programming Language :: Python :: 3.3
Classifier: Topic :: Database
